app/__init__.py
app/config.py
app/database.py
app/main.py
app/api/__init__.py
app/api/pyclick_merchant.py
app/api/transaction.py
app/click/__init__.py
app/click/authorization.py
app/click/crud.py
app/click/methods_merchatnt_api.py
app/click/models.py
app/click/router.py
app/click/schema.py
app/click/status.py
app/click/utils.py
fastapi_click-1.0.0.dist-info/METADATA
fastapi_click-1.0.0.dist-info/WHEEL
fastapi_click-1.0.0.dist-info/top_level.txt
fastapi_click-1.0.0.dist-info/RECORD
